gnetcli_server_bin/__init__.py
gnetcli_server_bin/__main__.py
gnetcli_server_bin/_binary.py
gnetcli_server_bin/_bin/gnetcli_server
gnetcli_server_bin-1.2.2.dist-info/METADATA
gnetcli_server_bin-1.2.2.dist-info/WHEEL
gnetcli_server_bin-1.2.2.dist-info/entry_points.txt
gnetcli_server_bin-1.2.2.dist-info/top_level.txt
gnetcli_server_bin-1.2.2.dist-info/RECORD
