Metadata-Version: 2.4
Name: gnetcli-server-bin
Version: 1.2.2
Summary: Python shim for a prepackaged gnetcli_server binary.
Author: Fedor Zhukov
Requires-Python: >=3.10
